relpath/__init__.py
rel_path-1.0.3.dist-info/LICENSE
rel_path-1.0.3.dist-info/METADATA
rel_path-1.0.3.dist-info/WHEEL
rel_path-1.0.3.dist-info/RECORD
