Metadata-Version: 2.1
Name: rel-path
Version: 1.0.3
Summary: Get relative path.
Home-page: https://github.com/jifox/relpath
License: Apache-2.0
Author: Josef Fuchs
Author-email: josef.fuchs@j-fuchs.at
Requires-Python: >=3.8
Classifier: Development Status :: 5 - Production/Stable
Classifier: Intended Audience :: Developers
Classifier: License :: OSI Approved :: Apache Software License
Classifier: License :: OSI Approved :: MIT License
Classifier: Operating System :: POSIX :: Linux
Classifier: Programming Language :: Python :: 3
Classifier: Programming Language :: Python :: 3.8
Classifier: Programming Language :: Python :: 3.9
Classifier: Programming Language :: Python :: 3.10
Classifier: Programming Language :: Python :: 3.11
Classifier: Programming Language :: Python :: 3.12
Classifier: Topic :: Software Development :: Libraries
Classifier: Typing :: Typed
Requires-Dist: pathlib (>=1.0.1,<2.0.0)
Project-URL: Repository, https://github.com/jifox/relpath
